HISTORY.md
MANIFEST.in
README.md
setup.cfg
setup.py
versioneer.py
rqdatac_fund/__init__.py
rqdatac_fund/_version.py
rqdatac_fund/api.py
rqdatac_fund.egg-info/PKG-INFO
rqdatac_fund.egg-info/SOURCES.txt
rqdatac_fund.egg-info/dependency_links.txt
rqdatac_fund.egg-info/not-zip-safe
rqdatac_fund.egg-info/requires.txt
rqdatac_fund.egg-info/top_level.txt